ao3/__init__.py
ao3/ao3.py
ao3/fandom.py
ao3/tag.py
ao3/work.py
ao3_py-2025.1.12.dist-info/METADATA
ao3_py-2025.1.12.dist-info/WHEEL
ao3_py-2025.1.12.dist-info/licenses/LICENSE
ao3_py-2025.1.12.dist-info/RECORD
