Metadata-Version: 2.4
Name: ao3-py
Version: 2025.1.12
Summary: an unofficial python sdk for Archive Of Our Own (AO3)
License: MIT License
License-File: LICENSE
Requires-Python: >=3
Requires-Dist: beautifulsoup4
Requires-Dist: lxml
Requires-Dist: requests
